README.md
kedro_lsp/__init__.py
kedro_lsp/cli.py
kedro_lsp/server.py
kedro_lsp-0.2.0.dist-info/entry_points.txt
kedro_lsp-0.2.0.dist-info/LICENSE
kedro_lsp-0.2.0.dist-info/WHEEL
kedro_lsp-0.2.0.dist-info/METADATA
kedro_lsp-0.2.0.dist-info/RECORD
