Metadata-Version: 2.1
Name: kedro-lsp
Version: 0.2.0
Summary: Kedro Language Server
Home-page: https://github.com/Kedro-Zero-to-Hero/kedro-lsp
License: MIT
Keywords: python,kedro,lsp,language-server-protocol
Author: Lim Hoang
Author-email: limdauto@gmail.com
Requires-Python: >=3.6.2,<3.9
Classifier: Development Status :: 4 - Beta
Classifier: Intended Audience :: Developers
Classifier: License :: OSI Approved :: MIT License
Classifier: Operating System :: OS Independent
Classifier: Programming Language :: Python :: 3
Classifier: Programming Language :: Python :: 3.7
Classifier: Programming Language :: Python :: 3.8
Classifier: Topic :: Software Development :: Libraries :: Python Modules
Classifier: Topic :: Text Editors :: Integrated Development Environments (IDE)
Classifier: Topic :: Utilities
Classifier: Typing :: Typed
Requires-Dist: kedro (>=0.17.3,<0.18.0)
Requires-Dist: pygls (>=0.10.3,<0.11.0)
Project-URL: Repository, https://github.com/Kedro-Zero-to-Hero/kedro-lsp
